sphinx_graphiql/__init__.py
sphinx_graphiql/sphinx_graphiql.py
sphinx_graphiql-0.0.3.dist-info/METADATA
sphinx_graphiql-0.0.3.dist-info/RECORD
sphinx_graphiql-0.0.3.dist-info/WHEEL
sphinx_graphiql-0.0.3.dist-info/top_level.txt
