Metadata-Version: 2.1
Name: sphinx-graphiql
Version: 0.0.3
Summary: Sphinx extension for GraphiQL
Home-page: https://github.com/hasura/sphinx_graphiql
Author: Rikin K
Author-email: rikin@hasura.io
License: UNKNOWN
Platform: UNKNOWN
Classifier: Programming Language :: Python :: 2.7
Classifier: License :: OSI Approved :: MIT License
Classifier: Operating System :: OS Independent
